README
setup.py
scripts/spdyathome
spdyathome/__init__.py
spdyathome/client.py
spdyathome/conf.py
spdyathome/serverbase.py
spdyathome/servers.py
spdyathome/urilib.py
spdyathome/util.py
spdyathome.egg-info/PKG-INFO
spdyathome.egg-info/SOURCES.txt
spdyathome.egg-info/dependency_links.txt
spdyathome.egg-info/not-zip-safe
spdyathome.egg-info/requires.txt
spdyathome.egg-info/top_level.txt