Metadata-Version: 1.1
Name: spdyathome
Version: 1.1.8
Summary: A simple script to run in order to collect data for comparing SPDY and HTTP
Home-page: http://github.com/bis12/spdyathome
Author: Brian Stack
Author-email: bis12@case.edu
License: MIT
Platform: UNKNOWN
Classifier: Development Status :: 4 - Beta
Classifier: License :: OSI Approved :: MIT License
Classifier: Programming Language :: Python :: 2.7
Provides: spdyathome
